MANIFEST.in
README.rst
setup.py
PyGNS3.egg-info/PKG-INFO
PyGNS3.egg-info/SOURCES.txt
PyGNS3.egg-info/dependency_links.txt
PyGNS3.egg-info/requires.txt
PyGNS3.egg-info/top_level.txt
pygns3/__init__.py
pygns3/controller.py
test/test_controller.py