Metadata-Version: 1.1
Name: PyGNS3
Version: 0.2.0.dev0
Summary: UNKNOWN
Home-page: https://github.com/mvdwoord/PyGNS3
Author: mvdwrd
Author-email: maarten@vanderwoord.nl
License: Unlicense
Platform: UNKNOWN
Classifier: Development Status :: 3 - Alpha
Classifier: License :: OSI Approved :: MIT License
Classifier: Programming Language :: Python :: 3.6
Classifier: Topic :: Software Development :: Libraries
